python_marconiclient-0.0.2.dist-info/WHEEL
python_marconiclient-0.0.2.dist-info/top_level.txt
python_marconiclient-0.0.2.dist-info/RECORD
python_marconiclient-0.0.2.dist-info/METADATA
python_marconiclient-0.0.2.dist-info/DESCRIPTION.rst
python_marconiclient-0.0.2.dist-info/metadata.json
python_marconiclient-0.0.2.dist-info/entry_points.txt
marconiclient/__init__.py
marconiclient/errors.py
marconiclient/version.py
marconiclient/tests/__init__.py
marconiclient/tests/base.py
marconiclient/tests/transport/dummy.py
marconiclient/tests/transport/__init__.py
marconiclient/tests/transport/api.py
marconiclient/tests/queues/messages.py
marconiclient/tests/queues/queues.py
marconiclient/tests/queues/shard.py
marconiclient/tests/queues/__init__.py
marconiclient/tests/queues/base.py
marconiclient/tests/queues/claims.py
marconiclient/tests/mock/message.py
marconiclient/tests/mock/__init__.py
marconiclient/auth/keystone.py
marconiclient/auth/__init__.py
marconiclient/auth/base.py
marconiclient/transport/response.py
marconiclient/transport/http.py
marconiclient/transport/__init__.py
marconiclient/transport/errors.py
marconiclient/transport/base.py
marconiclient/transport/api.py
marconiclient/transport/request.py
marconiclient/common/http.py
marconiclient/common/__init__.py
marconiclient/queues/client.py
marconiclient/queues/__init__.py
marconiclient/queues/cli.py
marconiclient/queues/v1/client.py
marconiclient/queues/v1/claim.py
marconiclient/queues/v1/queues.py
marconiclient/queues/v1/core.py
marconiclient/queues/v1/message.py
marconiclient/queues/v1/shard.py
marconiclient/queues/v1/__init__.py
marconiclient/queues/v1/iterator.py
marconiclient/queues/v1/cli.py
marconiclient/queues/v1/api.py
marconiclient/openstack/__init__.py
marconiclient/openstack/common/importutils.py
marconiclient/openstack/common/__init__.py
